{
  "project_info": {
    "project_number": "1033966813085",
    "project_id": "reboot-22979",
    "storage_bucket": "reboot-22979.appspot.com"
  },
  "client": [
    {
      "client_info": {
        "mobilesdk_app_id": "1:1033966813085:android:342b548061640bb25f3974",
        "android_client_info": {
          "package_name": "io.ionic.rider"
        }
      },
      "oauth_client": [
        {
          "client_id": "1033966813085-fu8jpt0la5qcpr7prughnmd2nle48q4d.apps.googleusercontent.com",
          "client_type": 3
        }
      ],
      "api_key": [
        {
          "current_key": "AIzaSyC3VpqBmNqCUe1_g_ELb-LASUYR98s9h5k"
        }
      ],
      "services": {
        "appinvite_service": {
          "other_platform_oauth_client": [
            {
              "client_id": "1033966813085-fu8jpt0la5qcpr7prughnmd2nle48q4d.apps.googleusercontent.com",
              "client_type": 3
            }
          ]
        }
      }
    }
  ],
  "configuration_version": "1"
}